PubChmAPI/__init__.py
pubchmapi-0.0.48.dist-info/licenses/LICENCE.txt
pubchmapi-0.0.48.dist-info/METADATA
pubchmapi-0.0.48.dist-info/WHEEL
pubchmapi-0.0.48.dist-info/top_level.txt
pubchmapi-0.0.48.dist-info/RECORD
