Metadata-Version: 2.4
Name: PubChmAPI
Version: 0.0.48
Summary: Simplifies interaction with the PubChem database via PUG-REST API.
Home-page: https://github.com/ahmed1212212/PubChmAPI
Author: Ahmed Alhilal
Author-email: aalhilal@kfu.edu.sa
License: MIT
Project-URL: Source, https://github.com/ahmed1212212/PubChmAPI
Project-URL: Tracker, https://github.com/ahmed1212212/PubChmAPI/issues
Keywords: cheminformatics pubchem api biology chemistry drug-discovery
Classifier: Development Status :: 5 - Production/Stable
Classifier: Intended Audience :: Education
Classifier: Intended Audience :: Science/Research
Classifier: Operating System :: OS Independent
Classifier: Operating System :: Microsoft :: Windows :: Windows 10
Classifier: License :: OSI Approved :: MIT License
Classifier: Programming Language :: Python :: 3
Classifier: Topic :: Scientific/Engineering :: Bio-Informatics
Classifier: Topic :: Scientific/Engineering :: Chemistry
Requires-Python: >=3.7
License-File: LICENCE.txt
Requires-Dist: requests>=2.25.0
Dynamic: author
Dynamic: author-email
Dynamic: classifier
Dynamic: description
Dynamic: description-content-type
Dynamic: home-page
Dynamic: keywords
Dynamic: license
Dynamic: license-file
Dynamic: project-url
Dynamic: requires-dist
Dynamic: requires-python
Dynamic: summary
